{
  "$schema": "https://json-schema.org/draft/2020-12/schema",
  "$id": "https://vivero-control.local/contracts/schemas/error-controlado.schema.json",
  "title": "Error controlado de operación",
  "type": "object",
  "additionalProperties": false,
  "required": ["code", "message"],
  "properties": {
    "code": {
      "type": "string",
      "enum": [
        "UNAUTHENTICATED",
        "INVALID_ARGUMENT",
        "USER_NOT_FOUND",
        "USER_INACTIVE",
        "PERMISSION_DENIED",
        "JOURNEY_NOT_FOUND",
        "JOURNEY_NOT_ACTIVE",
        "JOURNEY_NOT_DRAFT",
        "JOURNEY_NAME_REQUIRED",
        "JOURNEY_DRAFT_ACCESS_DENIED",
        "JOURNEY_ACCESS_DENIED",
        "JOURNEY_LINE_NOT_FOUND",
        "LINE_NOT_FOUND",
        "LINE_INACTIVE",
        "LINE_ALREADY_IN_ACTIVE_JOURNEY",
        "DUPLICATE_LINE_IDS",
        "PARTICIPANT_NOT_FOUND",
        "PARTICIPANT_INACTIVE",
        "DUPLICATE_PARTICIPANT_IDS",
        "ACTIVATION_STALE_SUMMARY",
        "ACTIVATION_SELECTIONS_INCOMPLETE",
        "ACTIVATION_LINES_REQUIRED",
        "ACTIVATION_COUNTER_REQUIRED",
        "ACTIVATION_REVIEWER_REQUIRED",
        "ACTIVATION_LIMIT_EXCEEDED",
        "ACTIVATION_PARTICIPANT_NOT_FOUND",
        "ACTIVATION_PARTICIPANT_INACTIVE",
        "ACTIVATION_PARTICIPANT_ROLE_CHANGED",
        "ACTIVATION_LINE_NOT_FOUND",
        "ACTIVATION_LINE_INACTIVE",
        "ACTIVATION_LINE_OCCUPIED",
        "JOURNEY_CLOSE_ACCESS_DENIED",
        "JOURNEY_CLOSE_STALE_VERSION",
        "JOURNEY_CLOSE_PENDING_LINES",
        "JOURNEY_CLOSE_ACTIVE_RESERVATIONS",
        "JOURNEY_CLOSE_PENDING_CORRECTIONS",
        "JOURNEY_CLOSE_LIMIT_EXCEEDED",
        "JOURNEY_CLOSE_OCCUPATION_MISMATCH",
        "DRAFT_CANCELLATION_REASON_REQUIRED",
        "DRAFT_CANCELLATION_STALE_VERSION",
        "DRAFT_CANCELLATION_INVALID_STATE",
        "DRAFT_CANCELLATION_OPERATIONAL_DATA_EXISTS",
        "DRAFT_REOPEN_STALE_VERSION",
        "DRAFT_REOPEN_INVALID_STATE",
        "DRAFT_REOPEN_NOT_ALLOWED",
        "USER_PROFILE_STALE_VERSION",
        "SELF_DEACTIVATION_FORBIDDEN",
        "SELF_ADMIN_ROLE_REMOVAL_FORBIDDEN",
        "LAST_ACTIVE_ADMIN_REQUIRED",
        "USER_ROLE_CHANGE_BLOCKED_ACTIVE_WORK",
        "USER_PROFILE_NO_CHANGE",
        "USER_EMAIL_ALREADY_EXISTS",
        "USER_EMAIL_INVALID",
        "USER_PASSWORD_WEAK",
        "CATALOG_LOCATION_NOT_FOUND",
        "CATALOG_LOCATION_INACTIVE",
        "CATALOG_LINE_NOT_FOUND",
        "CATALOG_STALE_VERSION",
        "CATALOG_DUPLICATE_CODE",
        "CATALOG_PARENT_CYCLE",
        "CATALOG_LOCATION_HAS_ACTIVE_CHILDREN",
        "CATALOG_LOCATION_HAS_ACTIVE_LINES",
        "CATALOG_LINE_OCCUPIED",
        "CATALOG_NO_CHANGE",
        "INVENTORY_INITIAL_LINE_INACTIVE",
        "INVENTORY_INITIAL_STALE_VERSION",
        "INVENTORY_ALREADY_EXISTS",
        "INVENTORY_INITIAL_ZERO_NOT_ALLOWED",
        "INVENTORY_INITIAL_SOURCE_INVALID",
        "INVENTORY_INITIAL_OPERATIONAL_ACTIVITY",
        "LINE_NOT_AVAILABLE",
        "RESERVATION_NOT_FOUND",
        "RESERVATION_NOT_ACTIVE",
        "RESERVATION_RELEASED",
        "RESERVATION_RELEASE_NOT_ALLOWED",
        "RESERVATION_RELEASE_REASON_REQUIRED",
        "RESERVATION_ALREADY_COUNTED",
        "RESERVATION_ACCESS_DENIED",
        "DEVICE_MISMATCH",
        "INVALID_RESERVATION_TOKEN",
        "LINE_RESERVATION_MISMATCH",
        "LINE_NOT_IN_COUNT",
        "COUNT_NOT_FOUND",
        "COUNT_NOT_RETURNED",
        "COUNT_AUTHOR_MISMATCH",
        "CORRECTION_RESPONSIBLE_MISMATCH",
        "CORRECTION_REASSIGNMENT_NOT_ALLOWED",
        "CORRECTION_ASSIGNEE_INACTIVE",
        "CORRECTION_ASSIGNEE_UNAUTHORIZED",
        "CORRECTION_REASSIGNMENT_REASON_REQUIRED",
        "CORRECTION_REASSIGNMENT_NO_CHANGE",
        "COUNT_NOT_PENDING_REVIEW",
        "COUNT_LINE_MISMATCH",
        "REVIEW_NOT_ALLOWED",
        "SELF_APPROVAL_FORBIDDEN",
        "EXCEPTION_REASON_REQUIRED",
        "RETURN_REASON_REQUIRED",
        "INVENTORY_NOT_FOUND",
        "ACTIVE_RESERVATION_EXISTS",
        "IDEMPOTENCY_CONFLICT",
        "ENVIRONMENT_NOT_ALLOWED",
        "INTERNAL_ERROR"
      ]
    },
    "message": {"type": "string", "minLength": 1, "maxLength": 240}
  }
}
